MANIFEST.in
README.textile
setup.py
appengine_template/VERSION
appengine_template/__init__.py
appengine_template/app.yaml
appengine_template/command.py
appengine_template/cron.yaml
appengine_template/django.zip
appengine_template/index.yaml
appengine_template/main.py
appengine_template/manage.py
appengine_template/settings.py
appengine_template/urls.py
appengine_template/appengine_django/__init__.py
appengine_template/appengine_django/mail.py
appengine_template/appengine_django/models.py
appengine_template/appengine_django/replacement_imp.py
appengine_template/appengine_django/auth/__init__.py
appengine_template/appengine_django/auth/decorators.py
appengine_template/appengine_django/auth/middleware.py
appengine_template/appengine_django/auth/models.py
appengine_template/appengine_django/auth/templatetags.py
appengine_template/appengine_django/auth/tests.py
appengine_template/appengine_django/conf/app_template/__init__.py
appengine_template/appengine_django/conf/app_template/models.py
appengine_template/appengine_django/conf/app_template/views.py
appengine_template/appengine_django/db/__init__.py
appengine_template/appengine_django/db/base.py
appengine_template/appengine_django/db/creation.py
appengine_template/appengine_django/management/__init__.py
appengine_template/appengine_django/management/commands/__init__.py
appengine_template/appengine_django/management/commands/console.py
appengine_template/appengine_django/management/commands/flush.py
appengine_template/appengine_django/management/commands/reset.py
appengine_template/appengine_django/management/commands/rollback.py
appengine_template/appengine_django/management/commands/runserver.py
appengine_template/appengine_django/management/commands/startapp.py
appengine_template/appengine_django/management/commands/testserver.py
appengine_template/appengine_django/management/commands/update.py
appengine_template/appengine_django/management/commands/vacuum_indexes.py
latimes_appengine_template.egg-info/PKG-INFO
latimes_appengine_template.egg-info/SOURCES.txt
latimes_appengine_template.egg-info/dependency_links.txt
latimes_appengine_template.egg-info/entry_points.txt
latimes_appengine_template.egg-info/top_level.txt