Metadata-Version: 1.0
Name: latimes-appengine-template
Version: 0.016
Summary: A basic template to start a new Django application hosted by Google App Engine.
Home-page: https://github.com/datadesk/latimes-appengine-template
Author: Ben Welsh
Author-email: ben.welsh@gmail.com
License: UNKNOWN
Download-URL: git@github.com:datadesk/latimes-appengine-template.git
Platform: UNKNOWN
